hapi/__init__.py
hapi/__version.py
hapi/cli.py
hapi/collect.py
hapi/core/__init__.py
hapi/core/commands.py
hapi/core/container.py
hapi/core/context.py
hapi/core/deployer.py
hapi/core/io.py
hapi/core/program.py
hapi/core/proxy.py
hapi/core/remote.py
hapi/core/task.py
hapi/exceptions.py
hapi/log/__init__.py
hapi/log/buffer_style.py
hapi/log/file_style.py
hapi/log/logger.py
hapi/log/none_style.py
hapi/recipe/__init__.py
hapi/recipe/__node.py
hapi/recipe/common.py
hapi/recipe/deploy/__init__.py
hapi/recipe/deploy/clean.py
hapi/recipe/deploy/code.py
hapi/recipe/deploy/end.py
hapi/recipe/deploy/env.py
hapi/recipe/deploy/lock.py
hapi/recipe/deploy/release.py
hapi/recipe/deploy/setup.py
hapi/recipe/deploy/shared.py
hapi/recipe/deploy/start.py
hapi/recipe/deploy/symlink.py
hapi/recipe/deploy/unlock.py
hapi/recipe/deploy/writable.py
hapi/recipe/express.py
hapi/recipe/laravel.py
hapi/recipe/php.py
hapi/utils.py
hapideploy-0.2.2.dist-info/entry_points.txt
hapideploy-0.2.2.dist-info/LICENSE.md
hapideploy-0.2.2.dist-info/METADATA
hapideploy-0.2.2.dist-info/WHEEL
hapideploy-0.2.2.dist-info/RECORD
