Metadata-Version: 2.3
Name: hapideploy
Version: 0.2.2
Summary: HapiDeploy is a remote execution tool written in Python, inspired by DeployPHP.
License: MIT
Author: Quynh Nguyen
Author-email: <seriquynh@gmail.com>
Requires-Python: >=3.13,<4.0
Classifier: License :: OSI Approved :: MIT License
Classifier: Programming Language :: Python :: 3
Classifier: Programming Language :: Python :: 3.13
Requires-Dist: fabric (>=3.2.2,<4.0)
Requires-Dist: pyyaml (>=6.0.2,<7.0)
Requires-Dist: typer (>=0.15.2,<1.0)
Requires-Dist: typing-extensions (>=4.12.2,<5.0)
